example.py
ofb_python_sdk/__init__.py
ofb_python_sdk/_version.py
ofb_python_sdk/client.py
sy_ofb_python_sdk-0.2.0.dist-info/LICENSE
sy_ofb_python_sdk-0.2.0.dist-info/METADATA
sy_ofb_python_sdk-0.2.0.dist-info/WHEEL
sy_ofb_python_sdk-0.2.0.dist-info/top_level.txt
sy_ofb_python_sdk-0.2.0.dist-info/RECORD
