Metadata-Version: 2.1
Name: sy-ofb-python-sdk
Version: 0.2.0
Summary: A Python interface for interacting with Microsoft's OneDrive.
Author-email: shingyu <xing_yv@outlook.com>
License: MIT License
Project-URL: homepage, https://github.com/shingyu/ofb-python-sdk
Project-URL: documentation, https://github.com/shingyu/ofb-python-sdk
Project-URL: repository, https://github.com/shingyu/ofb-python-sdk
Project-URL: issues, https://github.com/shingyu/ofb-python-sdk/issues
Keywords: one drive,microsoft,sdk,api,cloud,ofb,onedrive for business
Classifier: Development Status :: 4 - Beta
Classifier: Intended Audience :: Developers
Classifier: License :: OSI Approved :: MIT License
Classifier: Programming Language :: Python :: 3
Classifier: Programming Language :: Python :: 3.8
Classifier: Programming Language :: Python :: 3.9
Classifier: Programming Language :: Python :: 3.10
Classifier: Programming Language :: Python :: 3.11
Classifier: Programming Language :: Python :: 3.12
Requires-Python: >=3.8
License-File: LICENSE
Requires-Dist: requests
Requires-Dist: rich
